conceptnet_client/__init__.py
conceptnet_client/api.py
conceptnet_client/models/__init__.py
conceptnet_client/models/edge.py
conceptnet_client/models/edge_group.py
conceptnet_client/models/node.py
conceptnet_client/models/relation_group.py
conceptnet_client-0.1.0.dist-info/licenses/LICENSE
conceptnet_client-0.1.0.dist-info/METADATA
conceptnet_client-0.1.0.dist-info/WHEEL
conceptnet_client-0.1.0.dist-info/top_level.txt
conceptnet_client-0.1.0.dist-info/RECORD
