Metadata-Version: 2.4
Name: conceptnet-client
Version: 0.1.0
Summary: A Pythonic, object-oriented client for the ConceptNet API
Author-email: Alireza Mousiani <a.mousiani@gmail.com>
License: MIT License
Project-URL: Homepage, https://github.com/aalireza83/conceptnet-client
Project-URL: Source, https://github.com/aalireza83/conceptnet-client
Project-URL: Issues, https://github.com/aalireza83/conceptnet-client/issues
Requires-Python: >=3.7
License-File: LICENSE
Requires-Dist: requests
Dynamic: license-file
